cell_tools/__init__.py
cell_tools/_RNA/__init__.py
cell_tools/_RNA/_funcs/_calculate_differential_gene_expression.py
cell_tools/_RNA/_funcs/_calculate_running_quantile.py
cell_tools/_RNA/_funcs/_filter_cells.py
cell_tools/_RNA/_funcs/_filter_cells_by_gene_set.py
cell_tools/_RNA/_funcs/_filter_static_genes.py
cell_tools/_RNA/_funcs/_find_marker_genes.py
cell_tools-0.0.21.dist-info/LICENSE
cell_tools-0.0.21.dist-info/METADATA
cell_tools-0.0.21.dist-info/WHEEL
cell_tools-0.0.21.dist-info/top_level.txt
cell_tools-0.0.21.dist-info/RECORD
