Metadata-Version: 2.1
Name: cell-tools
Version: 0.0.21
Summary: cell_tools - Analysis Tools for Single-Cell Data
Home-page: https://github.com/mvinyard/cell-tools
Author: Michael E. Vinyard - Harvard University - Massachussetts General Hospital - Broad Institute of MIT and Harvard
Author-email: mvinyard@broadinstitute.org
License: MIT
Platform: UNKNOWN
Classifier: Development Status :: 2 - Pre-Alpha
Classifier: Programming Language :: Python :: 3.7
Classifier: Intended Audience :: Science/Research
Classifier: Topic :: Scientific/Engineering :: Bio-Informatics
Requires-Python: >3.7.0
License-File: LICENSE
Requires-Dist: anndata (>=0.7.8)
Requires-Dist: cython (>=0.29.24)
Requires-Dist: episcanpy (>=0.3.2)
Requires-Dist: nb-black (>=1.0.7)
Requires-Dist: pyranges (>=0.0.113)
Requires-Dist: licorice (>=0.0.2)
Requires-Dist: pydk (>=0.0.4)
Requires-Dist: vinplots (>=0.0.43)
Requires-Dist: tqdm (>=4.62.3)
